properties_tools/__init__.py
properties_tools/color.py
properties_tools/diff.py
properties_tools/patch.py
properties_tools/utils.py
properties_tools-0.7.2.dist-info/entry_points.txt
properties_tools-0.7.2.dist-info/LICENSE
properties_tools-0.7.2.dist-info/WHEEL
properties_tools-0.7.2.dist-info/METADATA
properties_tools-0.7.2.dist-info/RECORD
