Metadata-Version: 2.1
Name: properties-tools
Version: 0.7.2
Summary: Collection of command line tools to work with properties files (diff-like, patch-like)
Home-page: https://github.com/essembeh/properties-tools
License: Apache-2.0
Author: Sébastien MB
Author-email: seb@essembeh.org
Requires-Python: >=3.8,<4.0
Classifier: Development Status :: 4 - Beta
Classifier: License :: OSI Approved :: Apache Software License
Classifier: Programming Language :: Python :: 3
Classifier: Programming Language :: Python :: 3.8
Classifier: Programming Language :: Python :: 3.9
Classifier: Programming Language :: Python :: 3.10
Classifier: Programming Language :: Python :: 3.11
Classifier: Topic :: Software Development
Classifier: Topic :: Utilities
Requires-Dist: colorama (>=0.4.6,<0.5.0)
